odoo/addons/web_timeline/README.rst
odoo/addons/web_timeline/__init__.py
odoo/addons/web_timeline/__manifest__.py
odoo/addons/web_timeline/i18n/es.po
odoo/addons/web_timeline/i18n/fr.po
odoo/addons/web_timeline/i18n/he.po
odoo/addons/web_timeline/i18n/hr.po
odoo/addons/web_timeline/i18n/nl_NL.po
odoo/addons/web_timeline/i18n/pt.po
odoo/addons/web_timeline/i18n/pt_BR.po
odoo/addons/web_timeline/i18n/sk_SK.po
odoo/addons/web_timeline/i18n/web_timeline.pot
odoo/addons/web_timeline/i18n/zh_CN.po
odoo/addons/web_timeline/models/__init__.py
odoo/addons/web_timeline/models/ir_ui_view.py
odoo/addons/web_timeline/readme/CONFIGURE.rst
odoo/addons/web_timeline/readme/CONTRIBUTORS.rst
odoo/addons/web_timeline/readme/DESCRIPTION.rst
odoo/addons/web_timeline/readme/ROADMAP.rst
odoo/addons/web_timeline/readme/USAGE.rst
odoo/addons/web_timeline/static/description/icon.png
odoo/addons/web_timeline/static/description/index.html
odoo/addons/web_timeline/static/lib/vis-timeline/vis-timeline-graph2d.css
odoo/addons/web_timeline/static/lib/vis-timeline/vis-timeline-graph2d.js
odoo/addons/web_timeline/static/src/js/timeline_canvas.js
odoo/addons/web_timeline/static/src/js/timeline_controller.js
odoo/addons/web_timeline/static/src/js/timeline_model.js
odoo/addons/web_timeline/static/src/js/timeline_renderer.js
odoo/addons/web_timeline/static/src/js/timeline_view.js
odoo/addons/web_timeline/static/src/scss/web_timeline.scss
odoo/addons/web_timeline/static/src/xml/web_timeline.xml
odoo/addons/web_timeline/views/web_timeline.xml
odoo13_addon_web_timeline-13.0.1.1.2.dist-info/METADATA
odoo13_addon_web_timeline-13.0.1.1.2.dist-info/WHEEL
odoo13_addon_web_timeline-13.0.1.1.2.dist-info/top_level.txt
odoo13_addon_web_timeline-13.0.1.1.2.dist-info/RECORD
